odoo8_addon_partner_employee_quantity-8.0.1.0.0.99.dev13-py3.8-nspkg.pth
odoo_addons/partner_employee_quantity/README.rst
odoo_addons/partner_employee_quantity/__init__.py
odoo_addons/partner_employee_quantity/__openerp__.py
odoo_addons/partner_employee_quantity/i18n/de.po
odoo_addons/partner_employee_quantity/i18n/es.po
odoo_addons/partner_employee_quantity/i18n/eu.po
odoo_addons/partner_employee_quantity/i18n/fi.po
odoo_addons/partner_employee_quantity/i18n/it.po
odoo_addons/partner_employee_quantity/i18n/partner_employee_quantity.pot
odoo_addons/partner_employee_quantity/i18n/sl.po
odoo_addons/partner_employee_quantity/models/__init__.py
odoo_addons/partner_employee_quantity/models/res_partner.py
odoo_addons/partner_employee_quantity/security/ir.model.access.csv
odoo_addons/partner_employee_quantity/static/description/icon.png
odoo_addons/partner_employee_quantity/views/res_partner_employee_quantity_range_view.xml
odoo_addons/partner_employee_quantity/views/res_partner_view.xml
odoo8_addon_partner_employee_quantity-8.0.1.0.0.99.dev13.dist-info/METADATA
odoo8_addon_partner_employee_quantity-8.0.1.0.0.99.dev13.dist-info/WHEEL
odoo8_addon_partner_employee_quantity-8.0.1.0.0.99.dev13.dist-info/namespace_packages.txt
odoo8_addon_partner_employee_quantity-8.0.1.0.0.99.dev13.dist-info/top_level.txt
odoo8_addon_partner_employee_quantity-8.0.1.0.0.99.dev13.dist-info/RECORD
